s4u.image-2.4.0-py2.7-nspkg.pth
s4u/image/__init__.py
s4u/image/model.py
s4u/image/scale.py
s4u/image/testing.py
s4u/image/upgrade.py
s4u/image/util.py
s4u/image/tests/__init__.py
s4u/image/tests/test_init.py
s4u/image/tests/test_model.py
s4u/image/tests/test_scale.py
s4u/image/tests/test_upgrade.py
s4u/image/tests/test_util.py
s4u.image-2.4.0.dist-info/DESCRIPTION.rst
s4u.image-2.4.0.dist-info/METADATA
s4u.image-2.4.0.dist-info/metadata.json
s4u.image-2.4.0.dist-info/namespace_packages.txt
s4u.image-2.4.0.dist-info/RECORD
s4u.image-2.4.0.dist-info/top_level.txt
s4u.image-2.4.0.dist-info/WHEEL
